baudream/__init__.py
baudream/__main__.py
baudream/baudream.py
baudream/ressources/Plan_cours.pdf
baudream-1.0.0.dist-info/licenses/LICENSE
baudream-1.0.0.dist-info/METADATA
baudream-1.0.0.dist-info/WHEEL
baudream-1.0.0.dist-info/entry_points.txt
baudream-1.0.0.dist-info/top_level.txt
baudream-1.0.0.dist-info/RECORD
