Metadata-Version: 2.4
Name: baudream
Version: 1.0.0
Summary: Python package for the presentation of packet managers.
Author-email: xlav <cedric.guevremont@umontreal.ca>
License-Expression: MIT
Project-URL: Homepage, https://github.com/xlav94/baudream
Classifier: Programming Language :: Python :: 3
Classifier: Operating System :: OS Independent
Requires-Python: >=3.9
License-File: LICENSE
Requires-Dist: pybrowsers
Dynamic: license-file
